apish/__init__.py
apish/app.py
apish/base.py
apish/main.py
apish/metadata.py
apish/routes.py
apish/server.py
apish/utils.py
apish-0.5.1.data/data/VERSION
apish-0.5.1.dist-info/licenses/LICENSE
apish-0.5.1.dist-info/METADATA
apish-0.5.1.dist-info/WHEEL
apish-0.5.1.dist-info/top_level.txt
apish-0.5.1.dist-info/RECORD
